{
  "csv": "C:\\Users\\sihwa\\OneDrive\\바탕 화면\\기계학습프로젝\\처른레이더\\data\\processed\\baza_telecom_v2_bulgaria_public.csv",
  "rows": 8453,
  "features": 86,
  "churn_rate": 0.06494735596829528,
  "class_counts": {
    "no_churn": 7904,
    "churn": 549
  },
  "train_rows": 5071,
  "val_rows": 1691,
  "test_rows": 1691,
  "feature_groups": {
    "revenue_size": [
      "Total_SUBs",
      "AvgMobileRevenue",
      "AvgFIXRevenue",
      "TotalRevenue",
      "ARPU",
      "Mobile_Revenue_Ratio",
      "Fixed_Revenue_Ratio",
      "Revenue_Per_Sub",
      "Revenue_Per_Active",
      "Mobile_To_Fixed_Ratio",
      "Fixed_To_Mobile_Ratio",
      "Mobile_Only",
      "Fixed_Only"
    ],
    "subscriber_status": [
      "Active_subscribers",
      "Not_Active_subscribers",
      "Suspended_subscribers",
      "Active_Ratio",
      "Inactive_Ratio",
      "Suspended_Ratio",
      "Dormant_Ratio",
      "Has_Inactive",
      "Has_Suspended"
    ],
    "customer_profile": [
      "CRM_PID_Value_Segment",
      "EffectiveSegment",
      "Billing_ZIP",
      "KA_name"
    ],
    "geo_billing_zone": [
      "Billing_ZIP_norm",
      "bg_zip_found",
      "bg_place_count",
      "bg_place_name",
      "bg_admin1_name",
      "bg_admin1_code",
      "bg_admin2_name",
      "bg_admin2_code",
      "bg_admin3_name",
      "bg_admin3_code",
      "bg_latitude",
      "bg_longitude",
      "bg_geo_accuracy",
      "bg_distance_sofia_km",
      "bg_distance_plovdiv_km",
      "bg_distance_varna_km",
      "bg_distance_burgas_km",
      "bg_min_big_city_distance_km"
    ],
    "public_demographics": [
      "nsi_district_norm",
      "nsi_municipality_norm",
      "district_nsi_population_total",
      "district_nsi_population_male",
      "district_nsi_population_female",
      "district_nsi_population_urban",
      "district_nsi_population_rural",
      "district_nsi_population_male_ratio",
      "district_nsi_population_female_ratio",
      "district_nsi_population_urban_ratio",
      "district_nsi_population_rural_ratio",
      "district_nsi_workage_population_total",
      "district_nsi_under_working_age_total",
      "district_nsi_under_working_age_urban",
      "district_nsi_working_working_age_total",
      "district_nsi_working_working_age_urban",
      "district_nsi_over_working_age_total",
      "district_nsi_over_working_age_urban",
      "district_nsi_under_working_age_total_ratio",
      "district_nsi_working_working_age_total_ratio",
      "district_nsi_over_working_age_total_ratio",
      "municipality_nsi_population_total",
      "municipality_nsi_population_male",
      "municipality_nsi_population_female",
      "municipality_nsi_population_urban",
      "municipality_nsi_population_rural",
      "municipality_nsi_population_male_ratio",
      "municipality_nsi_population_female_ratio",
      "municipality_nsi_population_urban_ratio",
      "municipality_nsi_population_rural_ratio",
      "municipality_nsi_workage_population_total",
      "municipality_nsi_under_working_age_total",
      "municipality_nsi_under_working_age_urban",
      "municipality_nsi_working_working_age_total",
      "municipality_nsi_working_working_age_urban",
      "municipality_nsi_over_working_age_total",
      "municipality_nsi_over_working_age_urban",
      "municipality_nsi_under_working_age_total_ratio",
      "municipality_nsi_working_working_age_total_ratio",
      "municipality_nsi_over_working_age_total_ratio",
      "nsi_district_found",
      "nsi_municipality_found"
    ]
  },
  "random_forest_baseline": {
    "ablation": "all_features",
    "model": "random_forest",
    "feature_count": 86,
    "numeric_feature_count": 74,
    "categorical_feature_count": 12,
    "removed_feature_count": 0,
    "threshold": 0.47401869351240294,
    "val_best_f1": 0.17118997912317327,
    "test_oracle_threshold": 0.42942026240257575,
    "test_oracle_f1": 0.125,
    "test_roc_auc": 0.5040538209418666,
    "test_average_precision": 0.07247220242449633,
    "train_seconds": 2.439,
    "test_tuned_f1": 0.11416490486257928,
    "test_tuned_precision": 0.0743801652892562,
    "test_tuned_recall": 0.24545454545454545,
    "test_tuned_tn": 1245,
    "test_tuned_fp": 336,
    "test_tuned_fn": 83,
    "test_tuned_tp": 27,
    "test_tuned_pred_pos_rate": 0.21466587817859256,
    "test_default_f1": 0.08595988538681948,
    "test_default_precision": 0.06276150627615062,
    "test_default_recall": 0.13636363636363635,
    "test_default_tn": 1357,
    "test_default_fp": 224,
    "test_default_fn": 95,
    "test_default_tp": 15,
    "test_default_pred_pos_rate": 0.1413364872856298
  },
  "decision_tree_baseline": {
    "ablation": "all_features",
    "model": "decision_tree",
    "feature_count": 86,
    "numeric_feature_count": 74,
    "categorical_feature_count": 12,
    "removed_feature_count": 0,
    "threshold": 0.5163608645941089,
    "val_best_f1": 0.15950920245398773,
    "test_oracle_threshold": 0.0,
    "test_oracle_f1": 0.12215435868961688,
    "test_roc_auc": 0.5014576505088839,
    "test_average_precision": 0.06992372622807085,
    "train_seconds": 0.125,
    "test_tuned_f1": 0.12195121951219512,
    "test_tuned_precision": 0.07042253521126761,
    "test_tuned_recall": 0.45454545454545453,
    "test_tuned_tn": 921,
    "test_tuned_fp": 660,
    "test_tuned_fn": 60,
    "test_tuned_tp": 50,
    "test_tuned_pred_pos_rate": 0.41986989946777054,
    "test_default_f1": 0.12195121951219512,
    "test_default_precision": 0.07042253521126761,
    "test_default_recall": 0.45454545454545453,
    "test_default_tn": 921,
    "test_default_fp": 660,
    "test_default_fn": 60,
    "test_default_tp": 50,
    "test_default_pred_pos_rate": 0.41986989946777054
  },
  "top_random_forest_features": [
    "AvgMobileRevenue",
    "TotalRevenue",
    "ARPU",
    "Revenue_Per_Sub",
    "Revenue_Per_Active"
  ],
  "largest_f1_drop_ablation": {
    "ablation": "remove_group:customer_profile",
    "model": "random_forest",
    "feature_count": 82,
    "numeric_feature_count": 73,
    "categorical_feature_count": 9,
    "removed_feature_count": 4,
    "threshold": 0.5128464697314598,
    "val_best_f1": 0.16927899686520376,
    "test_oracle_threshold": 0.42589032971367174,
    "test_oracle_f1": 0.1242672919109027,
    "test_roc_auc": 0.5052900925766202,
    "test_average_precision": 0.07315271861469465,
    "train_seconds": 2.399,
    "test_tuned_f1": 0.1027190332326284,
    "test_tuned_precision": 0.07692307692307693,
    "test_tuned_recall": 0.15454545454545454,
    "test_tuned_tn": 1377,
    "test_tuned_fp": 204,
    "test_tuned_fn": 93,
    "test_tuned_tp": 17,
    "test_tuned_pred_pos_rate": 0.13069189828503844,
    "test_default_f1": 0.10215053763440861,
    "test_default_precision": 0.07251908396946564,
    "test_default_recall": 0.17272727272727273,
    "test_default_tn": 1338,
    "test_default_fp": 243,
    "test_default_fn": 91,
    "test_default_tp": 19,
    "test_default_pred_pos_rate": 0.15493790656416323,
    "removed_group": "customer_profile",
    "removed_features": "CRM_PID_Value_Segment;EffectiveSegment;Billing_ZIP;KA_name",
    "delta_f1_vs_rf_baseline": -0.01144587162995088,
    "delta_auc_vs_rf_baseline": 0.001236271634753594
  },
  "elapsed_seconds": 20.662,
  "importance_path": "C:\\Users\\sihwa\\OneDrive\\바탕 화면\\기계학습프로젝\\처른레이더\\results\\baza_public_feature_importance.csv",
  "group_importance_path": "C:\\Users\\sihwa\\OneDrive\\바탕 화면\\기계학습프로젝\\처른레이더\\results\\baza_public_feature_group_importance.csv",
  "ablation_path": "C:\\Users\\sihwa\\OneDrive\\바탕 화면\\기계학습프로젝\\처른레이더\\results\\baza_public_feature_ablation.csv"
}